<?xml version = '1.0' encoding = 'UTF-8'?>
<Relation class="oracle.dbtools.crest.model.design.logical.InheritanceRelation" name="Hierarchy_2" directorySegmentName="seg_0" id="42AED5EA-09AF-07F2-3B55-4709D863B984">
<createdBy>Ahmad</createdBy>
<createdTime>2021-11-07 04:12:24 UTC</createdTime>
<ownerDesignName>Dental_Clinic_Datal_Model</ownerDesignName>
<engineerTo>
<item key="1AD82F9A-862D-5DCF-4C00-A7878DE36F38" value="true"/>
</engineerTo>
<identifying>false</identifying>
<nameOnSource>Super Type</nameOnSource>
<nameOnTarget>Sub Type</nameOnTarget>
<optionalSource>true</optionalSource>
<optionalTarget>true</optionalTarget>
<sourceEntity>8DD50A94-0080-B913-1CE5-0906D927CAA8</sourceEntity>
<targetEntity>C283A1E5-5489-9977-C0CD-E41A10CC5D48</targetEntity>
<transferable>true</transferable>
<deleteRule>NO ACTION</deleteRule>
</Relation>